iflow_mcp_mcp_feishu_proj-0.1.8.dist-info/licenses/LICENSE
mcp_server/__init__.py
mcp_server/fsprojclient.py
mcp_server/server.py
mcp_server/test_server.py
iflow_mcp_mcp_feishu_proj-0.1.8.dist-info/METADATA
iflow_mcp_mcp_feishu_proj-0.1.8.dist-info/WHEEL
iflow_mcp_mcp_feishu_proj-0.1.8.dist-info/entry_points.txt
iflow_mcp_mcp_feishu_proj-0.1.8.dist-info/top_level.txt
iflow_mcp_mcp_feishu_proj-0.1.8.dist-info/RECORD
